CHANGELOG.txt
LICENCE.txt
MANIFEST.in
README.txt
setup.py
oceas/__init__.py
oceas/crypto.py
oceas.egg-info/PKG-INFO
oceas.egg-info/SOURCES.txt
oceas.egg-info/dependency_links.txt
oceas.egg-info/top_level.txt