Metadata-Version: 1.1
Name: oceas
Version: 0.0.2
Summary: A very basic
Home-page: UNKNOWN
Author: Melih Emin Kılıçoğlu
Author-email: melihemin10@gmail.com
License: MIT
Keywords: calculator
Platform: UNKNOWN
Classifier: Development Status :: 5 - Production/Stable
Classifier: Intended Audience :: Education
Classifier: Operating System :: Microsoft :: Windows :: Windows 10
Classifier: License :: OSI Approved :: MIT License
Classifier: Programming Language :: Python :: 3
